bigzhu_py/__init__.py
bigzhu_py/file_z/__init__.py
bigzhu_py/file_z/csv_z.py
bigzhu_py/hosts.csv
bigzhu_py/print_z/__init__.py
bigzhu_py/print_z/now_print.py
bigzhu_py/print_z/table_print.py
bigzhu_py/telegram_z/__init__.py
bigzhu_py/telegram_z/define.py
bigzhu_py/telegram_z/send_message.py
bigzhu_py/telegram_z/send_photo.py
bigzhu_py/time_z/__init__.py
bigzhu_py/time_z/now.py
bigzhu_py-0.1.3.dist-info/METADATA
bigzhu_py-0.1.3.dist-info/WHEEL
bigzhu_py-0.1.3.dist-info/RECORD
